{
  "date": "2025-05-02",
  "projects": {
    "jane_portfolio": {
      "totalLinesAdded": 133,
      "totalLinesRemoved": 0,
      "totalActiveTime": 0,
      "files": {
        "f:\\jane_portfolio\\app\\page.tsx": [
          {
            "timestamp": "2025-05-02T00:05:26.542Z",
            "fileName": "f:\\jane_portfolio\\app\\page.tsx",
            "fileType": ".tsx",
            "linesAdded": 133,
            "linesRemoved": 0,
            "projectName": "jane_portfolio",
            "content": {
              "added": [],
              "removed": []
            },
            "duration": 0,
            "language": "tsx"
          }
        ]
      },
      "languageStats": {
        "tsx": 0
      },
      "changeFrequency": {
        "0": 0
      },
      "topFiles": [
        "f:\\jane_portfolio\\app\\page.tsx"
      ],
      "averageChangeSize": 133
    },
    "niten": {
      "totalLinesAdded": 3645,
      "totalLinesRemoved": 1015,
      "totalActiveTime": 221,
      "files": {
        "f:\\niten\\frontend\\package.json": [
          {
            "timestamp": "2025-05-02T00:17:23.079Z",
            "fileName": "f:\\niten\\frontend\\package.json",
            "fileType": ".json",
            "linesAdded": 5,
            "linesRemoved": 0,
            "projectName": "niten",
            "content": {
              "added": [],
              "removed": []
            },
            "duration": 0,
            "language": "json"
          },
          {
            "timestamp": "2025-05-02T00:21:13.430Z",
            "fileName": "f:\\niten\\frontend\\package.json",
            "fileType": ".json",
            "linesAdded": 3,
            "linesRemoved": 0,
            "projectName": "niten",
            "content": {
              "added": [],
              "removed": []
            },
            "duration": 4,
            "language": "json"
          },
          {
            "timestamp": "2025-05-02T00:21:54.302Z",
            "fileName": "f:\\niten\\frontend\\package.json",
            "fileType": ".json",
            "linesAdded": 1,
            "linesRemoved": 0,
            "projectName": "niten",
            "content": {
              "added": [],
              "removed": []
            },
            "duration": 1,
            "language": "json"
          },
          {
            "timestamp": "2025-05-02T00:22:02.102Z",
            "fileName": "f:\\niten\\frontend\\package.json",
            "fileType": ".json",
            "linesAdded": 8,
            "linesRemoved": 0,
            "projectName": "niten",
            "content": {
              "added": [],
              "removed": []
            },
            "duration": 1,
            "language": "json"
          }
        ],
        "f:\\niten\\frontend\\.husky\\pre-commit": [
          {
            "timestamp": "2025-05-02T00:35:36.067Z",
            "fileName": "f:\\niten\\frontend\\.husky\\pre-commit",
            "fileType": "unknown",
            "linesAdded": 0,
            "linesRemoved": 3,
            "projectName": "niten",
            "content": {
              "added": [],
              "removed": []
            },
            "duration": 0,
            "language": "unknown"
          },
          {
            "timestamp": "2025-05-02T00:37:37.446Z",
            "fileName": "f:\\niten\\frontend\\.husky\\pre-commit",
            "fileType": "unknown",
            "linesAdded": 3,
            "linesRemoved": 0,
            "projectName": "niten",
            "content": {
              "added": [],
              "removed": []
            },
            "duration": 3,
            "language": "unknown"
          },
          {
            "timestamp": "2025-05-02T00:38:41.472Z",
            "fileName": "f:\\niten\\frontend\\.husky\\pre-commit",
            "fileType": "unknown",
            "linesAdded": 0,
            "linesRemoved": 1,
            "projectName": "niten",
            "content": {
              "added": [],
              "removed": []
            },
            "duration": 2,
            "language": "unknown"
          },
          {
            "timestamp": "2025-05-02T00:43:21.333Z",
            "fileName": "f:\\niten\\frontend\\.husky\\pre-commit",
            "fileType": "unknown",
            "linesAdded": 1,
            "linesRemoved": 0,
            "projectName": "niten",
            "content": {
              "added": [],
              "removed": []
            },
            "duration": 5,
            "language": "unknown"
          }
        ],
        "f:\\niten\\frontend\\app\\layout.tsx": [
          {
            "timestamp": "2025-05-02T01:05:37.781Z",
            "fileName": "f:\\niten\\frontend\\app\\layout.tsx",
            "fileType": ".tsx",
            "linesAdded": 1,
            "linesRemoved": 0,
            "projectName": "niten",
            "content": {
              "added": [],
              "removed": []
            },
            "duration": 0,
            "language": "tsx"
          },
          {
            "timestamp": "2025-05-02T01:07:32.603Z",
            "fileName": "f:\\niten\\frontend\\app\\layout.tsx",
            "fileType": ".tsx",
            "linesAdded": 23,
            "linesRemoved": 0,
            "projectName": "niten",
            "content": {
              "added": [],
              "removed": []
            },
            "duration": 2,
            "language": "tsx"
          }
        ],
        "f:\\niten\\frontend\\tailwind.config.js": [
          {
            "timestamp": "2025-05-02T01:05:44.862Z",
            "fileName": "f:\\niten\\frontend\\tailwind.config.js",
            "fileType": ".js",
            "linesAdded": 1,
            "linesRemoved": 0,
            "projectName": "niten",
            "content": {
              "added": [],
              "removed": []
            },
            "duration": 1,
            "language": "js"
          },
          {
            "timestamp": "2025-05-02T01:07:32.631Z",
            "fileName": "f:\\niten\\frontend\\tailwind.config.js",
            "fileType": ".js",
            "linesAdded": 9,
            "linesRemoved": 0,
            "projectName": "niten",
            "content": {
              "added": [],
              "removed": []
            },
            "duration": 2,
            "language": "js"
          }
        ],
        "f:\\niten\\frontend\\components\\home\\Hero.tsx": [
          {
            "timestamp": "2025-05-02T01:05:47.137Z",
            "fileName": "f:\\niten\\frontend\\components\\home\\Hero.tsx",
            "fileType": ".tsx",
            "linesAdded": 56,
            "linesRemoved": 0,
            "projectName": "niten",
            "content": {
              "added": [],
              "removed": []
            },
            "duration": 1,
            "language": "tsx"
          },
          {
            "timestamp": "2025-05-02T01:36:24.574Z",
            "fileName": "f:\\niten\\frontend\\components\\home\\Hero.tsx",
            "fileType": ".tsx",
            "linesAdded": 1,
            "linesRemoved": 0,
            "projectName": "niten",
            "content": {
              "added": [],
              "removed": []
            },
            "duration": 0,
            "language": "tsx"
          },
          {
            "timestamp": "2025-05-02T02:13:59.592Z",
            "fileName": "f:\\niten\\frontend\\components\\home\\Hero.tsx",
            "fileType": ".tsx",
            "linesAdded": 18,
            "linesRemoved": 0,
            "projectName": "niten",
            "content": {
              "added": [],
              "removed": []
            },
            "duration": 0,
            "language": "tsx"
          },
          {
            "timestamp": "2025-05-02T02:16:33.619Z",
            "fileName": "f:\\niten\\frontend\\components\\home\\Hero.tsx",
            "fileType": ".tsx",
            "linesAdded": 0,
            "linesRemoved": 12,
            "projectName": "niten",
            "content": {
              "added": [],
              "removed": []
            },
            "duration": 3,
            "language": "tsx"
          },
          {
            "timestamp": "2025-05-02T02:22:40.735Z",
            "fileName": "f:\\niten\\frontend\\components\\home\\Hero.tsx",
            "fileType": ".tsx",
            "linesAdded": 3,
            "linesRemoved": 0,
            "projectName": "niten",
            "content": {
              "added": [],
              "removed": []
            },
            "duration": 3,
            "language": "tsx"
          },
          {
            "timestamp": "2025-05-02T02:27:30.536Z",
            "fileName": "f:\\niten\\frontend\\components\\home\\Hero.tsx",
            "fileType": ".tsx",
            "linesAdded": 24,
            "linesRemoved": 0,
            "projectName": "niten",
            "content": {
              "added": [],
              "removed": []
            },
            "duration": 5,
            "language": "tsx"
          },
          {
            "timestamp": "2025-05-02T13:51:54.739Z",
            "fileName": "f:\\niten\\frontend\\components\\home\\Hero.tsx",
            "fileType": ".tsx",
            "linesAdded": 90,
            "linesRemoved": 0,
            "projectName": "niten",
            "content": {
              "added": [],
              "removed": []
            },
            "duration": 1,
            "language": "tsx"
          },
          {
            "timestamp": "2025-05-02T13:53:29.353Z",
            "fileName": "f:\\niten\\frontend\\components\\home\\Hero.tsx",
            "fileType": ".tsx",
            "linesAdded": 0,
            "linesRemoved": 44,
            "projectName": "niten",
            "content": {
              "added": [],
              "removed": []
            },
            "duration": 1,
            "language": "tsx"
          },
          {
            "timestamp": "2025-05-02T13:55:29.807Z",
            "fileName": "f:\\niten\\frontend\\components\\home\\Hero.tsx",
            "fileType": ".tsx",
            "linesAdded": 52,
            "linesRemoved": 0,
            "projectName": "niten",
            "content": {
              "added": [],
              "removed": []
            },
            "duration": 2,
            "language": "tsx"
          },
          {
            "timestamp": "2025-05-02T13:55:39.171Z",
            "fileName": "f:\\niten\\frontend\\components\\home\\Hero.tsx",
            "fileType": ".tsx",
            "linesAdded": 0,
            "linesRemoved": 8,
            "projectName": "niten",
            "content": {
              "added": [],
              "removed": []
            },
            "duration": 1,
            "language": "tsx"
          },
          {
            "timestamp": "2025-05-02T14:17:46.057Z",
            "fileName": "f:\\niten\\frontend\\components\\home\\Hero.tsx",
            "fileType": ".tsx",
            "linesAdded": 5,
            "linesRemoved": 0,
            "projectName": "niten",
            "content": {
              "added": [],
              "removed": []
            },
            "duration": 2,
            "language": "tsx"
          },
          {
            "timestamp": "2025-05-02T14:19:15.369Z",
            "fileName": "f:\\niten\\frontend\\components\\home\\Hero.tsx",
            "fileType": ".tsx",
            "linesAdded": 6,
            "linesRemoved": 0,
            "projectName": "niten",
            "content": {
              "added": [],
              "removed": []
            },
            "duration": 2,
            "language": "tsx"
          },
          {
            "timestamp": "2025-05-02T14:36:04.388Z",
            "fileName": "f:\\niten\\frontend\\components\\home\\Hero.tsx",
            "fileType": ".tsx",
            "linesAdded": 0,
            "linesRemoved": 10,
            "projectName": "niten",
            "content": {
              "added": [],
              "removed": []
            },
            "duration": 1,
            "language": "tsx"
          }
        ],
        "f:\\niten\\frontend\\app\\[locale]\\layout.tsx": [
          {
            "timestamp": "2025-05-02T01:08:37.710Z",
            "fileName": "f:\\niten\\frontend\\app\\[locale]\\layout.tsx",
            "fileType": ".tsx",
            "linesAdded": 11,
            "linesRemoved": 0,
            "projectName": "niten",
            "content": {
              "added": [],
              "removed": []
            },
            "duration": 2,
            "language": "tsx"
          },
          {
            "timestamp": "2025-05-02T01:20:41.905Z",
            "fileName": "f:\\niten\\frontend\\app\\[locale]\\layout.tsx",
            "fileType": ".tsx",
            "linesAdded": 3,
            "linesRemoved": 0,
            "projectName": "niten",
            "content": {
              "added": [],
              "removed": []
            },
            "duration": 0,
            "language": "tsx"
          }
        ],
        "f:\\niten\\frontend\\app\\[locale]\\globals.css": [
          {
            "timestamp": "2025-05-02T01:39:52.053Z",
            "fileName": "f:\\niten\\frontend\\app\\[locale]\\globals.css",
            "fileType": ".css",
            "linesAdded": 6,
            "linesRemoved": 0,
            "projectName": "niten",
            "content": {
              "added": [],
              "removed": []
            },
            "duration": 4,
            "language": "css"
          },
          {
            "timestamp": "2025-05-02T01:40:48.570Z",
            "fileName": "f:\\niten\\frontend\\app\\[locale]\\globals.css",
            "fileType": ".css",
            "linesAdded": 0,
            "linesRemoved": 6,
            "projectName": "niten",
            "content": {
              "added": [],
              "removed": []
            },
            "duration": 1,
            "language": "css"
          },
          {
            "timestamp": "2025-05-02T01:42:10.179Z",
            "fileName": "f:\\niten\\frontend\\app\\[locale]\\globals.css",
            "fileType": ".css",
            "linesAdded": 1,
            "linesRemoved": 0,
            "projectName": "niten",
            "content": {
              "added": [],
              "removed": []
            },
            "duration": 2,
            "language": "css"
          },
          {
            "timestamp": "2025-05-02T01:54:58.485Z",
            "fileName": "f:\\niten\\frontend\\app\\[locale]\\globals.css",
            "fileType": ".css",
            "linesAdded": 3,
            "linesRemoved": 0,
            "projectName": "niten",
            "content": {
              "added": [],
              "removed": []
            },
            "duration": 0,
            "language": "css"
          }
        ],
        "f:\\niten\\frontend\\app\\globals.css": [
          {
            "timestamp": "2025-05-02T01:46:46.368Z",
            "fileName": "f:\\niten\\frontend\\app\\globals.css",
            "fileType": ".css",
            "linesAdded": 1,
            "linesRemoved": 0,
            "projectName": "niten",
            "content": {
              "added": [],
              "removed": []
            },
            "duration": 5,
            "language": "css"
          },
          {
            "timestamp": "2025-05-02T01:47:31.971Z",
            "fileName": "f:\\niten\\frontend\\app\\globals.css",
            "fileType": ".css",
            "linesAdded": 4,
            "linesRemoved": 0,
            "projectName": "niten",
            "content": {
              "added": [],
              "removed": []
            },
            "duration": 1,
            "language": "css"
          }
        ],
        "f:\\niten\\frontend\\components\\layout\\Navbar.tsx": [
          {
            "timestamp": "2025-05-02T01:46:48.209Z",
            "fileName": "f:\\niten\\frontend\\components\\layout\\Navbar.tsx",
            "fileType": ".tsx",
            "linesAdded": 148,
            "linesRemoved": 0,
            "projectName": "niten",
            "content": {
              "added": [],
              "removed": []
            },
            "duration": 5,
            "language": "tsx"
          },
          {
            "timestamp": "2025-05-02T01:47:23.427Z",
            "fileName": "f:\\niten\\frontend\\components\\layout\\Navbar.tsx",
            "fileType": ".tsx",
            "linesAdded": 7,
            "linesRemoved": 0,
            "projectName": "niten",
            "content": {
              "added": [],
              "removed": []
            },
            "duration": 1,
            "language": "tsx"
          },
          {
            "timestamp": "2025-05-02T01:56:55.283Z",
            "fileName": "f:\\niten\\frontend\\components\\layout\\Navbar.tsx",
            "fileType": ".tsx",
            "linesAdded": 2,
            "linesRemoved": 0,
            "projectName": "niten",
            "content": {
              "added": [],
              "removed": []
            },
            "duration": 2,
            "language": "tsx"
          },
          {
            "timestamp": "2025-05-02T02:03:39.419Z",
            "fileName": "f:\\niten\\frontend\\components\\layout\\Navbar.tsx",
            "fileType": ".tsx",
            "linesAdded": 6,
            "linesRemoved": 0,
            "projectName": "niten",
            "content": {
              "added": [],
              "removed": []
            },
            "duration": 0,
            "language": "tsx"
          },
          {
            "timestamp": "2025-05-02T02:05:15.341Z",
            "fileName": "f:\\niten\\frontend\\components\\layout\\Navbar.tsx",
            "fileType": ".tsx",
            "linesAdded": 0,
            "linesRemoved": 1,
            "projectName": "niten",
            "content": {
              "added": [],
              "removed": []
            },
            "duration": 2,
            "language": "tsx"
          },
          {
            "timestamp": "2025-05-02T02:06:36.540Z",
            "fileName": "f:\\niten\\frontend\\components\\layout\\Navbar.tsx",
            "fileType": ".tsx",
            "linesAdded": 2,
            "linesRemoved": 0,
            "projectName": "niten",
            "content": {
              "added": [],
              "removed": []
            },
            "duration": 2,
            "language": "tsx"
          },
          {
            "timestamp": "2025-05-02T02:08:54.773Z",
            "fileName": "f:\\niten\\frontend\\components\\layout\\Navbar.tsx",
            "fileType": ".tsx",
            "linesAdded": 0,
            "linesRemoved": 5,
            "projectName": "niten",
            "content": {
              "added": [],
              "removed": []
            },
            "duration": 3,
            "language": "tsx"
          },
          {
            "timestamp": "2025-05-02T10:00:09.297Z",
            "fileName": "f:\\niten\\frontend\\components\\layout\\Navbar.tsx",
            "fileType": ".tsx",
            "linesAdded": 0,
            "linesRemoved": 2,
            "projectName": "niten",
            "content": {
              "added": [],
              "removed": []
            },
            "duration": 0,
            "language": "tsx"
          }
        ],
        "f:\\niten\\frontend\\components\\ui\\CountUp.tsx": [
          {
            "timestamp": "2025-05-02T02:20:02.449Z",
            "fileName": "f:\\niten\\frontend\\components\\ui\\CountUp.tsx",
            "fileType": ".tsx",
            "linesAdded": 1,
            "linesRemoved": 0,
            "projectName": "niten",
            "content": {
              "added": [],
              "removed": []
            },
            "duration": 4,
            "language": "tsx"
          },
          {
            "timestamp": "2025-05-02T02:20:10.052Z",
            "fileName": "f:\\niten\\frontend\\components\\ui\\CountUp.tsx",
            "fileType": ".tsx",
            "linesAdded": 97,
            "linesRemoved": 0,
            "projectName": "niten",
            "content": {
              "added": [],
              "removed": []
            },
            "duration": 1,
            "language": "tsx"
          },
          {
            "timestamp": "2025-05-02T02:28:17.521Z",
            "fileName": "f:\\niten\\frontend\\components\\ui\\CountUp.tsx",
            "fileType": ".tsx",
            "linesAdded": 1,
            "linesRemoved": 0,
            "projectName": "niten",
            "content": {
              "added": [],
              "removed": []
            },
            "duration": 1,
            "language": "tsx"
          },
          {
            "timestamp": "2025-05-02T13:51:33.307Z",
            "fileName": "f:\\niten\\frontend\\components\\ui\\CountUp.tsx",
            "fileType": ".tsx",
            "linesAdded": 99,
            "linesRemoved": 0,
            "projectName": "niten",
            "content": {
              "added": [],
              "removed": []
            },
            "duration": 0,
            "language": "tsx"
          },
          {
            "timestamp": "2025-05-02T13:52:14.599Z",
            "fileName": "f:\\niten\\frontend\\components\\ui\\CountUp.tsx",
            "fileType": ".tsx",
            "linesAdded": 0,
            "linesRemoved": 64,
            "projectName": "niten",
            "content": {
              "added": [],
              "removed": []
            },
            "duration": 1,
            "language": "tsx"
          },
          {
            "timestamp": "2025-05-02T13:53:42.972Z",
            "fileName": "f:\\niten\\frontend\\components\\ui\\CountUp.tsx",
            "fileType": ".tsx",
            "linesAdded": 64,
            "linesRemoved": 0,
            "projectName": "niten",
            "content": {
              "added": [],
              "removed": []
            },
            "duration": 1,
            "language": "tsx"
          }
        ],
        "f:\\niten\\frontend\\components\\home\\Features.tsx": [
          {
            "timestamp": "2025-05-02T02:36:08.194Z",
            "fileName": "f:\\niten\\frontend\\components\\home\\Features.tsx",
            "fileType": ".tsx",
            "linesAdded": 60,
            "linesRemoved": 0,
            "projectName": "niten",
            "content": {
              "added": [],
              "removed": []
            },
            "duration": 0,
            "language": "tsx"
          },
          {
            "timestamp": "2025-05-02T02:36:23.568Z",
            "fileName": "f:\\niten\\frontend\\components\\home\\Features.tsx",
            "fileType": ".tsx",
            "linesAdded": 1,
            "linesRemoved": 0,
            "projectName": "niten",
            "content": {
              "added": [],
              "removed": []
            },
            "duration": 1,
            "language": "tsx"
          },
          {
            "timestamp": "2025-05-02T02:43:02.616Z",
            "fileName": "f:\\niten\\frontend\\components\\home\\Features.tsx",
            "fileType": ".tsx",
            "linesAdded": 17,
            "linesRemoved": 0,
            "projectName": "niten",
            "content": {
              "added": [],
              "removed": []
            },
            "duration": 4,
            "language": "tsx"
          },
          {
            "timestamp": "2025-05-02T02:46:47.046Z",
            "fileName": "f:\\niten\\frontend\\components\\home\\Features.tsx",
            "fileType": ".tsx",
            "linesAdded": 0,
            "linesRemoved": 1,
            "projectName": "niten",
            "content": {
              "added": [],
              "removed": []
            },
            "duration": 4,
            "language": "tsx"
          },
          {
            "timestamp": "2025-05-02T14:08:28.832Z",
            "fileName": "f:\\niten\\frontend\\components\\home\\Features.tsx",
            "fileType": ".tsx",
            "linesAdded": 77,
            "linesRemoved": 0,
            "projectName": "niten",
            "content": {
              "added": [],
              "removed": []
            },
            "duration": 1,
            "language": "tsx"
          },
          {
            "timestamp": "2025-05-02T14:09:45.920Z",
            "fileName": "f:\\niten\\frontend\\components\\home\\Features.tsx",
            "fileType": ".tsx",
            "linesAdded": 0,
            "linesRemoved": 2,
            "projectName": "niten",
            "content": {
              "added": [],
              "removed": []
            },
            "duration": 2,
            "language": "tsx"
          },
          {
            "timestamp": "2025-05-02T14:11:04.981Z",
            "fileName": "f:\\niten\\frontend\\components\\home\\Features.tsx",
            "fileType": ".tsx",
            "linesAdded": 2,
            "linesRemoved": 0,
            "projectName": "niten",
            "content": {
              "added": [],
              "removed": []
            },
            "duration": 1,
            "language": "tsx"
          },
          {
            "timestamp": "2025-05-02T14:11:26.773Z",
            "fileName": "f:\\niten\\frontend\\components\\home\\Features.tsx",
            "fileType": ".tsx",
            "linesAdded": 2,
            "linesRemoved": 0,
            "projectName": "niten",
            "content": {
              "added": [],
              "removed": []
            },
            "duration": 1,
            "language": "tsx"
          },
          {
            "timestamp": "2025-05-02T14:16:31.012Z",
            "fileName": "f:\\niten\\frontend\\components\\home\\Features.tsx",
            "fileType": ".tsx",
            "linesAdded": 2,
            "linesRemoved": 0,
            "projectName": "niten",
            "content": {
              "added": [],
              "removed": []
            },
            "duration": 0,
            "language": "tsx"
          },
          {
            "timestamp": "2025-05-02T14:35:38.420Z",
            "fileName": "f:\\niten\\frontend\\components\\home\\Features.tsx",
            "fileType": ".tsx",
            "linesAdded": 0,
            "linesRemoved": 3,
            "projectName": "niten",
            "content": {
              "added": [],
              "removed": []
            },
            "duration": 1,
            "language": "tsx"
          }
        ],
        "f:\\niten\\frontend\\components\\ui\\button.tsx": [
          {
            "timestamp": "2025-05-02T02:39:20.869Z",
            "fileName": "f:\\niten\\frontend\\components\\ui\\button.tsx",
            "fileType": ".tsx",
            "linesAdded": 58,
            "linesRemoved": 0,
            "projectName": "niten",
            "content": {
              "added": [],
              "removed": []
            },
            "duration": 3,
            "language": "tsx"
          },
          {
            "timestamp": "2025-05-02T02:39:23.568Z",
            "fileName": "f:\\niten\\frontend\\components\\ui\\button.tsx",
            "fileType": ".tsx",
            "linesAdded": 1,
            "linesRemoved": 0,
            "projectName": "niten",
            "content": {
              "added": [],
              "removed": []
            },
            "duration": 1,
            "language": "tsx"
          }
        ],
        "f:\\niten\\frontend\\components\\home\\Testimonials.tsx": [
          {
            "timestamp": "2025-05-02T02:50:05.419Z",
            "fileName": "f:\\niten\\frontend\\components\\home\\Testimonials.tsx",
            "fileType": ".tsx",
            "linesAdded": 199,
            "linesRemoved": 0,
            "projectName": "niten",
            "content": {
              "added": [],
              "removed": []
            },
            "duration": 4,
            "language": "tsx"
          },
          {
            "timestamp": "2025-05-02T02:50:15.589Z",
            "fileName": "f:\\niten\\frontend\\components\\home\\Testimonials.tsx",
            "fileType": ".tsx",
            "linesAdded": 0,
            "linesRemoved": 1,
            "projectName": "niten",
            "content": {
              "added": [],
              "removed": []
            },
            "duration": 1,
            "language": "tsx"
          },
          {
            "timestamp": "2025-05-02T12:45:22.649Z",
            "fileName": "f:\\niten\\frontend\\components\\home\\Testimonials.tsx",
            "fileType": ".tsx",
            "linesAdded": 0,
            "linesRemoved": 168,
            "projectName": "niten",
            "content": {
              "added": [],
              "removed": []
            },
            "duration": 1,
            "language": "tsx"
          },
          {
            "timestamp": "2025-05-02T12:52:47.215Z",
            "fileName": "f:\\niten\\frontend\\components\\home\\Testimonials.tsx",
            "fileType": ".tsx",
            "linesAdded": 168,
            "linesRemoved": 0,
            "projectName": "niten",
            "content": {
              "added": [],
              "removed": []
            },
            "duration": 1,
            "language": "tsx"
          },
          {
            "timestamp": "2025-05-02T12:58:55.062Z",
            "fileName": "f:\\niten\\frontend\\components\\home\\Testimonials.tsx",
            "fileType": ".tsx",
            "linesAdded": 0,
            "linesRemoved": 145,
            "projectName": "niten",
            "content": {
              "added": [],
              "removed": []
            },
            "duration": 4,
            "language": "tsx"
          },
          {
            "timestamp": "2025-05-02T12:59:38.029Z",
            "fileName": "f:\\niten\\frontend\\components\\home\\Testimonials.tsx",
            "fileType": ".tsx",
            "linesAdded": 145,
            "linesRemoved": 0,
            "projectName": "niten",
            "content": {
              "added": [],
              "removed": []
            },
            "duration": 1,
            "language": "tsx"
          },
          {
            "timestamp": "2025-05-02T13:01:30.950Z",
            "fileName": "f:\\niten\\frontend\\components\\home\\Testimonials.tsx",
            "fileType": ".tsx",
            "linesAdded": 0,
            "linesRemoved": 145,
            "projectName": "niten",
            "content": {
              "added": [],
              "removed": []
            },
            "duration": 2,
            "language": "tsx"
          },
          {
            "timestamp": "2025-05-02T13:01:51.357Z",
            "fileName": "f:\\niten\\frontend\\components\\home\\Testimonials.tsx",
            "fileType": ".tsx",
            "linesAdded": 145,
            "linesRemoved": 0,
            "projectName": "niten",
            "content": {
              "added": [],
              "removed": []
            },
            "duration": 1,
            "language": "tsx"
          },
          {
            "timestamp": "2025-05-02T13:06:16.195Z",
            "fileName": "f:\\niten\\frontend\\components\\home\\Testimonials.tsx",
            "fileType": ".tsx",
            "linesAdded": 0,
            "linesRemoved": 145,
            "projectName": "niten",
            "content": {
              "added": [],
              "removed": []
            },
            "duration": 5,
            "language": "tsx"
          },
          {
            "timestamp": "2025-05-02T13:28:51.473Z",
            "fileName": "f:\\niten\\frontend\\components\\home\\Testimonials.tsx",
            "fileType": ".tsx",
            "linesAdded": 0,
            "linesRemoved": 27,
            "projectName": "niten",
            "content": {
              "added": [],
              "removed": []
            },
            "duration": 3,
            "language": "tsx"
          },
          {
            "timestamp": "2025-05-02T14:06:17.466Z",
            "fileName": "f:\\niten\\frontend\\components\\home\\Testimonials.tsx",
            "fileType": ".tsx",
            "linesAdded": 26,
            "linesRemoved": 0,
            "projectName": "niten",
            "content": {
              "added": [],
              "removed": []
            },
            "duration": 0,
            "language": "tsx"
          },
          {
            "timestamp": "2025-05-02T14:06:45.551Z",
            "fileName": "f:\\niten\\frontend\\components\\home\\Testimonials.tsx",
            "fileType": ".tsx",
            "linesAdded": 8,
            "linesRemoved": 0,
            "projectName": "niten",
            "content": {
              "added": [],
              "removed": []
            },
            "duration": 1,
            "language": "tsx"
          },
          {
            "timestamp": "2025-05-02T14:36:22.885Z",
            "fileName": "f:\\niten\\frontend\\components\\home\\Testimonials.tsx",
            "fileType": ".tsx",
            "linesAdded": 0,
            "linesRemoved": 7,
            "projectName": "niten",
            "content": {
              "added": [],
              "removed": []
            },
            "duration": 1,
            "language": "tsx"
          }
        ],
        "f:\\niten\\frontend\\components\\layout\\Footer.tsx": [
          {
            "timestamp": "2025-05-02T02:55:06.348Z",
            "fileName": "f:\\niten\\frontend\\components\\layout\\Footer.tsx",
            "fileType": ".tsx",
            "linesAdded": 145,
            "linesRemoved": 0,
            "projectName": "niten",
            "content": {
              "added": [],
              "removed": []
            },
            "duration": 5,
            "language": "tsx"
          },
          {
            "timestamp": "2025-05-02T14:20:50.219Z",
            "fileName": "f:\\niten\\frontend\\components\\layout\\Footer.tsx",
            "fileType": ".tsx",
            "linesAdded": 145,
            "linesRemoved": 0,
            "projectName": "niten",
            "content": {
              "added": [],
              "removed": []
            },
            "duration": 2,
            "language": "tsx"
          }
        ],
        "f:\\niten\\frontend\\components\\services\\ServiceCard.tsx": [
          {
            "timestamp": "2025-05-02T11:59:43.441Z",
            "fileName": "f:\\niten\\frontend\\components\\services\\ServiceCard.tsx",
            "fileType": ".tsx",
            "linesAdded": 111,
            "linesRemoved": 0,
            "projectName": "niten",
            "content": {
              "added": [],
              "removed": []
            },
            "duration": 0,
            "language": "tsx"
          },
          {
            "timestamp": "2025-05-02T12:06:16.232Z",
            "fileName": "f:\\niten\\frontend\\components\\services\\ServiceCard.tsx",
            "fileType": ".tsx",
            "linesAdded": 2,
            "linesRemoved": 0,
            "projectName": "niten",
            "content": {
              "added": [],
              "removed": []
            },
            "duration": 2,
            "language": "tsx"
          }
        ],
        "f:\\niten\\frontend\\components\\services\\ServiceGrid.tsx": [
          {
            "timestamp": "2025-05-02T12:04:21.593Z",
            "fileName": "f:\\niten\\frontend\\components\\services\\ServiceGrid.tsx",
            "fileType": ".tsx",
            "linesAdded": 68,
            "linesRemoved": 0,
            "projectName": "niten",
            "content": {
              "added": [],
              "removed": []
            },
            "duration": 5,
            "language": "tsx"
          }
        ],
        "f:\\niten\\frontend\\data\\testimonials.ts": [
          {
            "timestamp": "2025-05-02T12:44:38.647Z",
            "fileName": "f:\\niten\\frontend\\data\\testimonials.ts",
            "fileType": ".ts",
            "linesAdded": 1,
            "linesRemoved": 0,
            "projectName": "niten",
            "content": {
              "added": [],
              "removed": []
            },
            "duration": 0,
            "language": "ts"
          },
          {
            "timestamp": "2025-05-02T12:45:27.527Z",
            "fileName": "f:\\niten\\frontend\\data\\testimonials.ts",
            "fileType": ".ts",
            "linesAdded": 10,
            "linesRemoved": 0,
            "projectName": "niten",
            "content": {
              "added": [],
              "removed": []
            },
            "duration": 1,
            "language": "ts"
          }
        ],
        "f:\\niten\\frontend\\components\\client\\TestimonialsCarousel.tsx": [
          {
            "timestamp": "2025-05-02T12:44:44.664Z",
            "fileName": "f:\\niten\\frontend\\components\\client\\TestimonialsCarousel.tsx",
            "fileType": ".tsx",
            "linesAdded": 1,
            "linesRemoved": 0,
            "projectName": "niten",
            "content": {
              "added": [],
              "removed": []
            },
            "duration": 1,
            "language": "tsx"
          },
          {
            "timestamp": "2025-05-02T12:45:35.812Z",
            "fileName": "f:\\niten\\frontend\\components\\client\\TestimonialsCarousel.tsx",
            "fileType": ".tsx",
            "linesAdded": 35,
            "linesRemoved": 0,
            "projectName": "niten",
            "content": {
              "added": [],
              "removed": []
            },
            "duration": 1,
            "language": "tsx"
          },
          {
            "timestamp": "2025-05-02T12:52:06.227Z",
            "fileName": "f:\\niten\\frontend\\components\\client\\TestimonialsCarousel.tsx",
            "fileType": ".tsx",
            "linesAdded": 112,
            "linesRemoved": 0,
            "projectName": "niten",
            "content": {
              "added": [],
              "removed": []
            },
            "duration": 0,
            "language": "tsx"
          },
          {
            "timestamp": "2025-05-02T12:52:21.149Z",
            "fileName": "f:\\niten\\frontend\\components\\client\\TestimonialsCarousel.tsx",
            "fileType": ".tsx",
            "linesAdded": 0,
            "linesRemoved": 147,
            "projectName": "niten",
            "content": {
              "added": [],
              "removed": []
            },
            "duration": 1,
            "language": "tsx"
          }
        ],
        "f:\\niten\\frontend\\components\\home\\TestimonialsAnimation.tsx": [
          {
            "timestamp": "2025-05-02T12:55:08.694Z",
            "fileName": "f:\\niten\\frontend\\components\\home\\TestimonialsAnimation.tsx",
            "fileType": ".tsx",
            "linesAdded": 1,
            "linesRemoved": 0,
            "projectName": "niten",
            "content": {
              "added": [],
              "removed": []
            },
            "duration": 3,
            "language": "tsx"
          },
          {
            "timestamp": "2025-05-02T12:55:53.987Z",
            "fileName": "f:\\niten\\frontend\\components\\home\\TestimonialsAnimation.tsx",
            "fileType": ".tsx",
            "linesAdded": 164,
            "linesRemoved": 0,
            "projectName": "niten",
            "content": {
              "added": [],
              "removed": []
            },
            "duration": 1,
            "language": "tsx"
          },
          {
            "timestamp": "2025-05-02T13:39:19.786Z",
            "fileName": "f:\\niten\\frontend\\components\\home\\TestimonialsAnimation.tsx",
            "fileType": ".tsx",
            "linesAdded": 4,
            "linesRemoved": 0,
            "projectName": "niten",
            "content": {
              "added": [],
              "removed": []
            },
            "duration": 0,
            "language": "tsx"
          }
        ],
        "f:\\niten\\frontend\\messages\\fr\\home.json": [
          {
            "timestamp": "2025-05-02T13:26:32.471Z",
            "fileName": "f:\\niten\\frontend\\messages\\fr\\home.json",
            "fileType": ".json",
            "linesAdded": 60,
            "linesRemoved": 0,
            "projectName": "niten",
            "content": {
              "added": [],
              "removed": []
            },
            "duration": 0,
            "language": "json"
          },
          {
            "timestamp": "2025-05-02T13:29:02.761Z",
            "fileName": "f:\\niten\\frontend\\messages\\fr\\home.json",
            "fileType": ".json",
            "linesAdded": 23,
            "linesRemoved": 0,
            "projectName": "niten",
            "content": {
              "added": [],
              "removed": []
            },
            "duration": 1,
            "language": "json"
          }
        ],
        "f:\\niten\\frontend\\messages\\en\\home.json": [
          {
            "timestamp": "2025-05-02T13:30:18.815Z",
            "fileName": "f:\\niten\\frontend\\messages\\en\\home.json",
            "fileType": ".json",
            "linesAdded": 83,
            "linesRemoved": 0,
            "projectName": "niten",
            "content": {
              "added": [],
              "removed": []
            },
            "duration": 2,
            "language": "json"
          }
        ],
        "f:\\niten\\frontend\\components\\home\\StatsSection.tsx": [
          {
            "timestamp": "2025-05-02T13:51:41.326Z",
            "fileName": "f:\\niten\\frontend\\components\\home\\StatsSection.tsx",
            "fileType": ".tsx",
            "linesAdded": 1,
            "linesRemoved": 0,
            "projectName": "niten",
            "content": {
              "added": [],
              "removed": []
            },
            "duration": 1,
            "language": "tsx"
          },
          {
            "timestamp": "2025-05-02T13:52:50.704Z",
            "fileName": "f:\\niten\\frontend\\components\\home\\StatsSection.tsx",
            "fileType": ".tsx",
            "linesAdded": 43,
            "linesRemoved": 0,
            "projectName": "niten",
            "content": {
              "added": [],
              "removed": []
            },
            "duration": 1,
            "language": "tsx"
          }
        ],
        "f:\\niten\\frontend\\utils\\getTranslation.ts": [
          {
            "timestamp": "2025-05-02T13:56:00.090Z",
            "fileName": "f:\\niten\\frontend\\utils\\getTranslation.ts",
            "fileType": ".ts",
            "linesAdded": 1,
            "linesRemoved": 0,
            "projectName": "niten",
            "content": {
              "added": [],
              "removed": []
            },
            "duration": 1,
            "language": "ts"
          },
          {
            "timestamp": "2025-05-02T13:56:33.053Z",
            "fileName": "f:\\niten\\frontend\\utils\\getTranslation.ts",
            "fileType": ".ts",
            "linesAdded": 6,
            "linesRemoved": 0,
            "projectName": "niten",
            "content": {
              "added": [],
              "removed": []
            },
            "duration": 1,
            "language": "ts"
          }
        ],
        "f:\\niten\\frontend\\components\\home\\FeatureIcons.tsx": [
          {
            "timestamp": "2025-05-02T14:08:14.794Z",
            "fileName": "f:\\niten\\frontend\\components\\home\\FeatureIcons.tsx",
            "fileType": ".tsx",
            "linesAdded": 1,
            "linesRemoved": 0,
            "projectName": "niten",
            "content": {
              "added": [],
              "removed": []
            },
            "duration": 2,
            "language": "tsx"
          },
          {
            "timestamp": "2025-05-02T14:10:30.098Z",
            "fileName": "f:\\niten\\frontend\\components\\home\\FeatureIcons.tsx",
            "fileType": ".tsx",
            "linesAdded": 16,
            "linesRemoved": 0,
            "projectName": "niten",
            "content": {
              "added": [],
              "removed": []
            },
            "duration": 1,
            "language": "tsx"
          }
        ],
        "f:\\niten\\frontend\\components\\layout\\LanguageSwitcher.tsx": [
          {
            "timestamp": "2025-05-02T14:22:30.302Z",
            "fileName": "f:\\niten\\frontend\\components\\layout\\LanguageSwitcher.tsx",
            "fileType": ".tsx",
            "linesAdded": 49,
            "linesRemoved": 0,
            "projectName": "niten",
            "content": {
              "added": [],
              "removed": []
            },
            "duration": 2,
            "language": "tsx"
          }
        ],
        "f:\\niten\\frontend\\app\\[locale]\\services\\page.tsx": [
          {
            "timestamp": "2025-05-02T14:28:06.753Z",
            "fileName": "f:\\niten\\frontend\\app\\[locale]\\services\\page.tsx",
            "fileType": ".tsx",
            "linesAdded": 63,
            "linesRemoved": 0,
            "projectName": "niten",
            "content": {
              "added": [],
              "removed": []
            },
            "duration": 0,
            "language": "tsx"
          },
          {
            "timestamp": "2025-05-02T14:29:37.403Z",
            "fileName": "f:\\niten\\frontend\\app\\[locale]\\services\\page.tsx",
            "fileType": ".tsx",
            "linesAdded": 9,
            "linesRemoved": 0,
            "projectName": "niten",
            "content": {
              "added": [],
              "removed": []
            },
            "duration": 2,
            "language": "tsx"
          },
          {
            "timestamp": "2025-05-02T14:35:11.979Z",
            "fileName": "f:\\niten\\frontend\\app\\[locale]\\services\\page.tsx",
            "fileType": ".tsx",
            "linesAdded": 0,
            "linesRemoved": 8,
            "projectName": "niten",
            "content": {
              "added": [],
              "removed": []
            },
            "duration": 0,
            "language": "tsx"
          }
        ],
        "f:\\niten\\frontend\\app\\[locale]\\projects\\page.tsx": [
          {
            "timestamp": "2025-05-02T14:48:26.135Z",
            "fileName": "f:\\niten\\frontend\\app\\[locale]\\projects\\page.tsx",
            "fileType": ".tsx",
            "linesAdded": 97,
            "linesRemoved": 0,
            "projectName": "niten",
            "content": {
              "added": [],
              "removed": []
            },
            "duration": 0,
            "language": "tsx"
          },
          {
            "timestamp": "2025-05-02T15:18:31.612Z",
            "fileName": "f:\\niten\\frontend\\app\\[locale]\\projects\\page.tsx",
            "fileType": ".tsx",
            "linesAdded": 0,
            "linesRemoved": 2,
            "projectName": "niten",
            "content": {
              "added": [],
              "removed": []
            },
            "duration": 0,
            "language": "tsx"
          },
          {
            "timestamp": "2025-05-02T15:19:20.216Z",
            "fileName": "f:\\niten\\frontend\\app\\[locale]\\projects\\page.tsx",
            "fileType": ".tsx",
            "linesAdded": 0,
            "linesRemoved": 3,
            "projectName": "niten",
            "content": {
              "added": [],
              "removed": []
            },
            "duration": 1,
            "language": "tsx"
          },
          {
            "timestamp": "2025-05-02T15:21:25.401Z",
            "fileName": "f:\\niten\\frontend\\app\\[locale]\\projects\\page.tsx",
            "fileType": ".tsx",
            "linesAdded": 0,
            "linesRemoved": 2,
            "projectName": "niten",
            "content": {
              "added": [],
              "removed": []
            },
            "duration": 3,
            "language": "tsx"
          },
          {
            "timestamp": "2025-05-02T15:22:52.574Z",
            "fileName": "f:\\niten\\frontend\\app\\[locale]\\projects\\page.tsx",
            "fileType": ".tsx",
            "linesAdded": 2,
            "linesRemoved": 0,
            "projectName": "niten",
            "content": {
              "added": [],
              "removed": []
            },
            "duration": 2,
            "language": "tsx"
          },
          {
            "timestamp": "2025-05-02T15:25:10.514Z",
            "fileName": "f:\\niten\\frontend\\app\\[locale]\\projects\\page.tsx",
            "fileType": ".tsx",
            "linesAdded": 0,
            "linesRemoved": 5,
            "projectName": "niten",
            "content": {
              "added": [],
              "removed": []
            },
            "duration": 3,
            "language": "tsx"
          },
          {
            "timestamp": "2025-05-02T15:29:24.492Z",
            "fileName": "f:\\niten\\frontend\\app\\[locale]\\projects\\page.tsx",
            "fileType": ".tsx",
            "linesAdded": 4,
            "linesRemoved": 0,
            "projectName": "niten",
            "content": {
              "added": [],
              "removed": []
            },
            "duration": 5,
            "language": "tsx"
          }
        ],
        "f:\\niten\\frontend\\messages\\en\\projects.json": [
          {
            "timestamp": "2025-05-02T14:52:37.951Z",
            "fileName": "f:\\niten\\frontend\\messages\\en\\projects.json",
            "fileType": ".json",
            "linesAdded": 1,
            "linesRemoved": 0,
            "projectName": "niten",
            "content": {
              "added": [],
              "removed": []
            },
            "duration": 5,
            "language": "json"
          },
          {
            "timestamp": "2025-05-02T14:52:57.309Z",
            "fileName": "f:\\niten\\frontend\\messages\\en\\projects.json",
            "fileType": ".json",
            "linesAdded": 25,
            "linesRemoved": 0,
            "projectName": "niten",
            "content": {
              "added": [],
              "removed": []
            },
            "duration": 1,
            "language": "json"
          },
          {
            "timestamp": "2025-05-02T14:55:31.833Z",
            "fileName": "f:\\niten\\frontend\\messages\\en\\projects.json",
            "fileType": ".json",
            "linesAdded": 6,
            "linesRemoved": 0,
            "projectName": "niten",
            "content": {
              "added": [],
              "removed": []
            },
            "duration": 1,
            "language": "json"
          },
          {
            "timestamp": "2025-05-02T15:25:17.651Z",
            "fileName": "f:\\niten\\frontend\\messages\\en\\projects.json",
            "fileType": ".json",
            "linesAdded": 42,
            "linesRemoved": 0,
            "projectName": "niten",
            "content": {
              "added": [],
              "removed": []
            },
            "duration": 1,
            "language": "json"
          }
        ],
        "f:\\niten\\frontend\\components\\projects\\ProjectGrid.tsx": [
          {
            "timestamp": "2025-05-02T14:54:21.767Z",
            "fileName": "f:\\niten\\frontend\\components\\projects\\ProjectGrid.tsx",
            "fileType": ".tsx",
            "linesAdded": 96,
            "linesRemoved": 0,
            "projectName": "niten",
            "content": {
              "added": [],
              "removed": []
            },
            "duration": 2,
            "language": "tsx"
          },
          {
            "timestamp": "2025-05-02T14:55:53.988Z",
            "fileName": "f:\\niten\\frontend\\components\\projects\\ProjectGrid.tsx",
            "fileType": ".tsx",
            "linesAdded": 2,
            "linesRemoved": 0,
            "projectName": "niten",
            "content": {
              "added": [],
              "removed": []
            },
            "duration": 1,
            "language": "tsx"
          }
        ],
        "f:\\niten\\frontend\\components\\projects\\ProjectCard.tsx": [
          {
            "timestamp": "2025-05-02T14:54:33.859Z",
            "fileName": "f:\\niten\\frontend\\components\\projects\\ProjectCard.tsx",
            "fileType": ".tsx",
            "linesAdded": 104,
            "linesRemoved": 0,
            "projectName": "niten",
            "content": {
              "added": [],
              "removed": []
            },
            "duration": 1,
            "language": "tsx"
          },
          {
            "timestamp": "2025-05-02T14:55:44.238Z",
            "fileName": "f:\\niten\\frontend\\components\\projects\\ProjectCard.tsx",
            "fileType": ".tsx",
            "linesAdded": 3,
            "linesRemoved": 0,
            "projectName": "niten",
            "content": {
              "added": [],
              "removed": []
            },
            "duration": 1,
            "language": "tsx"
          },
          {
            "timestamp": "2025-05-02T15:40:19.716Z",
            "fileName": "f:\\niten\\frontend\\components\\projects\\ProjectCard.tsx",
            "fileType": ".tsx",
            "linesAdded": 5,
            "linesRemoved": 0,
            "projectName": "niten",
            "content": {
              "added": [],
              "removed": []
            },
            "duration": 5,
            "language": "tsx"
          },
          {
            "timestamp": "2025-05-02T15:49:18.608Z",
            "fileName": "f:\\niten\\frontend\\components\\projects\\ProjectCard.tsx",
            "fileType": ".tsx",
            "linesAdded": 3,
            "linesRemoved": 0,
            "projectName": "niten",
            "content": {
              "added": [],
              "removed": []
            },
            "duration": 0,
            "language": "tsx"
          },
          {
            "timestamp": "2025-05-02T15:52:00.529Z",
            "fileName": "f:\\niten\\frontend\\components\\projects\\ProjectCard.tsx",
            "fileType": ".tsx",
            "linesAdded": 0,
            "linesRemoved": 2,
            "projectName": "niten",
            "content": {
              "added": [],
              "removed": []
            },
            "duration": 3,
            "language": "tsx"
          },
          {
            "timestamp": "2025-05-02T15:52:13.989Z",
            "fileName": "f:\\niten\\frontend\\components\\projects\\ProjectCard.tsx",
            "fileType": ".tsx",
            "linesAdded": 2,
            "linesRemoved": 0,
            "projectName": "niten",
            "content": {
              "added": [],
              "removed": []
            },
            "duration": 1,
            "language": "tsx"
          }
        ],
        "f:\\niten\\frontend\\i18n\\request.ts": [
          {
            "timestamp": "2025-05-02T14:57:54.025Z",
            "fileName": "f:\\niten\\frontend\\i18n\\request.ts",
            "fileType": ".ts",
            "linesAdded": 27,
            "linesRemoved": 0,
            "projectName": "niten",
            "content": {
              "added": [],
              "removed": []
            },
            "duration": 3,
            "language": "ts"
          },
          {
            "timestamp": "2025-05-02T16:13:27.107Z",
            "fileName": "f:\\niten\\frontend\\i18n\\request.ts",
            "fileType": ".ts",
            "linesAdded": 1,
            "linesRemoved": 0,
            "projectName": "niten",
            "content": {
              "added": [],
              "removed": []
            },
            "duration": 1,
            "language": "ts"
          }
        ],
        "f:\\niten\\frontend\\messages\\fr\\projects.json": [
          {
            "timestamp": "2025-05-02T14:59:27.662Z",
            "fileName": "f:\\niten\\frontend\\messages\\fr\\projects.json",
            "fileType": ".json",
            "linesAdded": 1,
            "linesRemoved": 0,
            "projectName": "niten",
            "content": {
              "added": [],
              "removed": []
            },
            "duration": 2,
            "language": "json"
          },
          {
            "timestamp": "2025-05-02T14:59:29.770Z",
            "fileName": "f:\\niten\\frontend\\messages\\fr\\projects.json",
            "fileType": ".json",
            "linesAdded": 32,
            "linesRemoved": 0,
            "projectName": "niten",
            "content": {
              "added": [],
              "removed": []
            },
            "duration": 1,
            "language": "json"
          },
          {
            "timestamp": "2025-05-02T15:35:23.128Z",
            "fileName": "f:\\niten\\frontend\\messages\\fr\\projects.json",
            "fileType": ".json",
            "linesAdded": 43,
            "linesRemoved": 0,
            "projectName": "niten",
            "content": {
              "added": [],
              "removed": []
            },
            "duration": 0,
            "language": "json"
          }
        ],
        "f:\\niten\\frontend\\messages\\fr\\about.json": [
          {
            "timestamp": "2025-05-02T15:58:22.330Z",
            "fileName": "f:\\niten\\frontend\\messages\\fr\\about.json",
            "fileType": ".json",
            "linesAdded": 1,
            "linesRemoved": 0,
            "projectName": "niten",
            "content": {
              "added": [],
              "removed": []
            },
            "duration": 0,
            "language": "json"
          },
          {
            "timestamp": "2025-05-02T15:58:24.929Z",
            "fileName": "f:\\niten\\frontend\\messages\\fr\\about.json",
            "fileType": ".json",
            "linesAdded": 7,
            "linesRemoved": 0,
            "projectName": "niten",
            "content": {
              "added": [],
              "removed": []
            },
            "duration": 1,
            "language": "json"
          },
          {
            "timestamp": "2025-05-02T16:00:26.386Z",
            "fileName": "f:\\niten\\frontend\\messages\\fr\\about.json",
            "fileType": ".json",
            "linesAdded": 6,
            "linesRemoved": 0,
            "projectName": "niten",
            "content": {
              "added": [],
              "removed": []
            },
            "duration": 2,
            "language": "json"
          },
          {
            "timestamp": "2025-05-02T16:00:41.608Z",
            "fileName": "f:\\niten\\frontend\\messages\\fr\\about.json",
            "fileType": ".json",
            "linesAdded": 2,
            "linesRemoved": 0,
            "projectName": "niten",
            "content": {
              "added": [],
              "removed": []
            },
            "duration": 1,
            "language": "json"
          },
          {
            "timestamp": "2025-05-02T16:02:48.819Z",
            "fileName": "f:\\niten\\frontend\\messages\\fr\\about.json",
            "fileType": ".json",
            "linesAdded": 5,
            "linesRemoved": 0,
            "projectName": "niten",
            "content": {
              "added": [],
              "removed": []
            },
            "duration": 1,
            "language": "json"
          },
          {
            "timestamp": "2025-05-02T16:12:36.009Z",
            "fileName": "f:\\niten\\frontend\\messages\\fr\\about.json",
            "fileType": ".json",
            "linesAdded": 47,
            "linesRemoved": 0,
            "projectName": "niten",
            "content": {
              "added": [],
              "removed": []
            },
            "duration": 0,
            "language": "json"
          }
        ],
        "f:\\niten\\frontend\\messages\\en\\about.json": [
          {
            "timestamp": "2025-05-02T15:58:59.778Z",
            "fileName": "f:\\niten\\frontend\\messages\\en\\about.json",
            "fileType": ".json",
            "linesAdded": 1,
            "linesRemoved": 0,
            "projectName": "niten",
            "content": {
              "added": [],
              "removed": []
            },
            "duration": 1,
            "language": "json"
          },
          {
            "timestamp": "2025-05-02T15:59:04.934Z",
            "fileName": "f:\\niten\\frontend\\messages\\en\\about.json",
            "fileType": ".json",
            "linesAdded": 7,
            "linesRemoved": 0,
            "projectName": "niten",
            "content": {
              "added": [],
              "removed": []
            },
            "duration": 1,
            "language": "json"
          },
          {
            "timestamp": "2025-05-02T16:01:02.778Z",
            "fileName": "f:\\niten\\frontend\\messages\\en\\about.json",
            "fileType": ".json",
            "linesAdded": 6,
            "linesRemoved": 0,
            "projectName": "niten",
            "content": {
              "added": [],
              "removed": []
            },
            "duration": 1,
            "language": "json"
          },
          {
            "timestamp": "2025-05-02T16:02:32.179Z",
            "fileName": "f:\\niten\\frontend\\messages\\en\\about.json",
            "fileType": ".json",
            "linesAdded": 6,
            "linesRemoved": 0,
            "projectName": "niten",
            "content": {
              "added": [],
              "removed": []
            },
            "duration": 2,
            "language": "json"
          },
          {
            "timestamp": "2025-05-02T16:12:36.057Z",
            "fileName": "f:\\niten\\frontend\\messages\\en\\about.json",
            "fileType": ".json",
            "linesAdded": 47,
            "linesRemoved": 0,
            "projectName": "niten",
            "content": {
              "added": [],
              "removed": []
            },
            "duration": 0,
            "language": "json"
          }
        ],
        "f:\\niten\\frontend\\components\\about\\StatsSection.tsx": [
          {
            "timestamp": "2025-05-02T16:05:37.819Z",
            "fileName": "f:\\niten\\frontend\\components\\about\\StatsSection.tsx",
            "fileType": ".tsx",
            "linesAdded": 28,
            "linesRemoved": 0,
            "projectName": "niten",
            "content": {
              "added": [],
              "removed": []
            },
            "duration": 3,
            "language": "tsx"
          },
          {
            "timestamp": "2025-05-02T16:12:35.933Z",
            "fileName": "f:\\niten\\frontend\\components\\about\\StatsSection.tsx",
            "fileType": ".tsx",
            "linesAdded": 10,
            "linesRemoved": 0,
            "projectName": "niten",
            "content": {
              "added": [],
              "removed": []
            },
            "duration": 0,
            "language": "tsx"
          }
        ],
        "f:\\niten\\frontend\\components\\about\\Constants.tsx": [
          {
            "timestamp": "2025-05-02T16:19:04.576Z",
            "fileName": "f:\\niten\\frontend\\components\\about\\Constants.tsx",
            "fileType": ".tsx",
            "linesAdded": 59,
            "linesRemoved": 0,
            "projectName": "niten",
            "content": {
              "added": [],
              "removed": []
            },
            "duration": 0,
            "language": "tsx"
          },
          {
            "timestamp": "2025-05-02T16:19:12.663Z",
            "fileName": "f:\\niten\\frontend\\components\\about\\Constants.tsx",
            "fileType": ".tsx",
            "linesAdded": 0,
            "linesRemoved": 46,
            "projectName": "niten",
            "content": {
              "added": [],
              "removed": []
            },
            "duration": 1,
            "language": "tsx"
          },
          {
            "timestamp": "2025-05-02T16:19:31.481Z",
            "fileName": "f:\\niten\\frontend\\components\\about\\Constants.tsx",
            "fileType": ".tsx",
            "linesAdded": 46,
            "linesRemoved": 0,
            "projectName": "niten",
            "content": {
              "added": [],
              "removed": []
            },
            "duration": 1,
            "language": "tsx"
          }
        ],
        "f:\\niten\\frontend\\components\\about\\HeroSection.tsx": [
          {
            "timestamp": "2025-05-02T16:21:09.727Z",
            "fileName": "f:\\niten\\frontend\\components\\about\\HeroSection.tsx",
            "fileType": ".tsx",
            "linesAdded": 40,
            "linesRemoved": 0,
            "projectName": "niten",
            "content": {
              "added": [],
              "removed": []
            },
            "duration": 2,
            "language": "tsx"
          }
        ]
      },
      "languageStats": {
        "json": 0
      },
      "changeFrequency": {
        "0": 0
      },
      "topFiles": [
        "f:\\niten\\frontend\\package.json"
      ],
      "averageChangeSize": 5
    }
  },
  "totalActiveTime": 0,
  "totalProjects": 1,
  "totalFiles": 1,
  "mostActiveHours": [
    0
  ],
  "mostUsedLanguages": [
    "tsx"
  ]
}